django_postgrespool_lab-0.3.0.dist-info/metadata.json
django_postgrespool_lab-0.3.0.dist-info/WHEEL
django_postgrespool_lab-0.3.0.dist-info/top_level.txt
django_postgrespool_lab-0.3.0.dist-info/RECORD
django_postgrespool_lab-0.3.0.dist-info/DESCRIPTION.rst
django_postgrespool_lab-0.3.0.dist-info/METADATA
django_postgrespool/__init__.py
django_postgrespool/base.py
