Metadata-Version: 2.0
Name: django-postgrespool-lab
Version: 0.3.0
Summary: Postgres Connection Pooling for Django.
Home-page: https://github.com/kennethreitz/django-postgrespool
Author: Kenneth Reitz
Author-email: me@kennethreitz.com
License: MIT
Platform: UNKNOWN
Classifier: Intended Audience :: Developers
Classifier: Natural Language :: English
Classifier: License :: OSI Approved :: MIT License
Classifier: Programming Language :: Python
Classifier: Programming Language :: Python :: 2.7
Requires-Dist: psycopg2
Requires-Dist: sqlalchemy
